notifyurl/__init__.py
notifyurl/__main__.py
notifyurl/notify.py
notifyurl-0.0.2.dist-info/METADATA
notifyurl-0.0.2.dist-info/WHEEL
notifyurl-0.0.2.dist-info/entry_points.txt
notifyurl-0.0.2.dist-info/top_level.txt
notifyurl-0.0.2.dist-info/zip-safe
notifyurl-0.0.2.dist-info/RECORD
