Metadata-Version: 2.1
Name: notifyurl
Version: 0.0.2
Summary: a command line tool to notify via webhook
Home-page: UNKNOWN
Author: Yuchen Wu
Author-email: Curiosity_Wu@outlook.com
License: MIT
Keywords: notify
Platform: UNKNOWN
